notafunnytest/__init__.py
notafunnytest-1.1.dist-info/METADATA
notafunnytest-1.1.dist-info/WHEEL
notafunnytest-1.1.dist-info/top_level.txt
notafunnytest-1.1.dist-info/RECORD
