Metadata-Version: 2.1
Name: notafunnytest
Version: 1.1
Summary: The least funny joke in the world
Home-page: https://github.com/LorenzoPeve/notafunnytest
Author: Lorenzo Peve
Author-email: doesnotexist@gmail.com
License: MIT
Classifier: Programming Language :: Python :: 3
Classifier: Operating System :: OS Independent
